{"nodes": [{"id": "apps_orchestrator_src_reports_bradley_pipeline_ts", "label": "bradley-pipeline.ts", "file_type": "code", "source_file": "apps\\orchestrator\\src\\reports\\bradley-pipeline.ts", "source_location": "L1"}], "edges": [{"source": "apps_orchestrator_src_reports_bradley_pipeline_ts", "target": "apps_orchestrator_src_reports_types_ts", "relation": "imports_from", "confidence": "EXTRACTED", "source_file": "apps\\orchestrator\\src\\reports\\bradley-pipeline.ts", "source_location": "L1", "weight": 1.0}, {"source": "apps_orchestrator_src_reports_bradley_pipeline_ts", "target": "apps_orchestrator_src_reports_agents_runner_ts", "relation": "imports_from", "confidence": "EXTRACTED", "source_file": "apps\\orchestrator\\src\\reports\\bradley-pipeline.ts", "source_location": "L2", "weight": 1.0}]}